hien_logger/__init__.py
hien_logger/logger.py
hien_logger/utils.py
hien_logger-0.0.3.1.dist-info/LICENSE
hien_logger-0.0.3.1.dist-info/METADATA
hien_logger-0.0.3.1.dist-info/WHEEL
hien_logger-0.0.3.1.dist-info/top_level.txt
hien_logger-0.0.3.1.dist-info/RECORD
