Metadata-Version: 2.2
Name: hien_logger
Version: 0.0.3.1
Summary: A colorful logger for Python's applications.
Author-email: hienhayho <hienhayho3002@gmail.com>
Project-URL: Homepage, https://github.com/hienhayho/hien_logger
Project-URL: Issues, https://github.com/hienhayho/hien_logger/issues
Classifier: Programming Language :: Python :: 3
Classifier: License :: OSI Approved :: MIT License
Classifier: Operating System :: OS Independent
Requires-Python: >=3.8
License-File: LICENSE
Requires-Dist: click>=8.1.8
Requires-Dist: pytz>=2024.2
Requires-Dist: python-dotenv>=1.0.1
Requires-Dist: pytest>=8.3.4
